tstoolbox/__init__.py
tstoolbox/tstoolbox.py
tstoolbox/HydroErr/setup.py
tstoolbox/HydroErr/HydroErr/HydroErr.py
tstoolbox/HydroErr/HydroErr/__init__.py
tstoolbox/HydroErr/HydroErr/tests/tests.py
tstoolbox/HydroErr/docs/conf.py
tstoolbox/HydroErr/docs/latex_for_all_metrics.py
tstoolbox/functions/__init__.py
tstoolbox/functions/accumulate.py
tstoolbox/functions/add_trend.py
tstoolbox/functions/aggregate.py
tstoolbox/functions/calculate_fdc.py
tstoolbox/functions/calculate_kde.py
tstoolbox/functions/clip.py
tstoolbox/functions/convert.py
tstoolbox/functions/convert_index.py
tstoolbox/functions/convert_index_to_julian.py
tstoolbox/functions/converttz.py
tstoolbox/functions/correlation.py
tstoolbox/functions/createts.py
tstoolbox/functions/date_offset.py
tstoolbox/functions/date_slice.py
tstoolbox/functions/describe.py
tstoolbox/functions/dtw.py
tstoolbox/functions/equation.py
tstoolbox/functions/ewm_window.py
tstoolbox/functions/expanding_window.py
tstoolbox/functions/fill.py
tstoolbox/functions/filter.py
tstoolbox/functions/fit.py
tstoolbox/functions/gof.py
tstoolbox/functions/lag.py
tstoolbox/functions/normalization.py
tstoolbox/functions/pca.py
tstoolbox/functions/pct_change.py
tstoolbox/functions/peak_detection.py
tstoolbox/functions/pick.py
tstoolbox/functions/plot.py
tstoolbox/functions/rank.py
tstoolbox/functions/read.py
tstoolbox/functions/regression.py
tstoolbox/functions/remove_trend.py
tstoolbox/functions/replace.py
tstoolbox/functions/rolling_window.py
tstoolbox/functions/stack.py
tstoolbox/functions/stdtozrxp.py
tstoolbox/functions/tstopickle.py
tstoolbox/functions/unstack.py
tstoolbox/toolbox_utils/docs/conf.py
tstoolbox/toolbox_utils/src/toolbox_utils/__init__.py
tstoolbox/toolbox_utils/src/toolbox_utils/tsutils.py
tstoolbox/toolbox_utils/src/toolbox_utils/readers/__init__.py
tstoolbox/toolbox_utils/src/toolbox_utils/readers/hbn.py
tstoolbox/toolbox_utils/src/toolbox_utils/readers/plotgen.py
tstoolbox/toolbox_utils/src/toolbox_utils/readers/wdm.py
tstoolbox-108.2.1.dist-info/LICENSE.txt
tstoolbox-108.2.1.dist-info/METADATA
tstoolbox-108.2.1.dist-info/WHEEL
tstoolbox-108.2.1.dist-info/entry_points.txt
tstoolbox-108.2.1.dist-info/top_level.txt
tstoolbox-108.2.1.dist-info/RECORD
