Metadata-Version: 2.2
Name: tstoolbox
Version: 108.2.1
Summary: Command line script and Python library to manipulate time series.
Author-email: Tim Cera <tim@cerazone.net>
License: BSD-3-Clause
Project-URL: documentation, https://timcera.bitbucket.io/tstoolbox/docs/index.html#tstoolbox-documentation
Project-URL: github, https://github.com/timcera/tstoolbox
Project-URL: bitbucket, https://bitbucket.org/timcera/tstoolbox/src/main/
Keywords: time-series,cli-app,aggregate,fill,filter
Classifier: Development Status :: 5 - Production/Stable
Classifier: Intended Audience :: Science/Research
Classifier: Intended Audience :: End Users/Desktop
Classifier: Intended Audience :: Developers
Classifier: Environment :: Console
Classifier: License :: OSI Approved :: BSD License
Classifier: Natural Language :: English
Classifier: Operating System :: OS Independent
Classifier: Programming Language :: Python :: 3 :: Only
Classifier: Programming Language :: Python :: 3.8
Classifier: Programming Language :: Python :: 3.9
Classifier: Programming Language :: Python :: 3.10
Classifier: Programming Language :: Python :: 3.11
Classifier: Programming Language :: Python :: 3.12
Classifier: Topic :: Scientific/Engineering :: Information Analysis
Classifier: Topic :: Scientific/Engineering
Classifier: Topic :: Software Development :: Libraries :: Python Modules
Requires-Python: >=3.8
License-File: LICENSE.txt
Requires-Dist: cltoolbox>=1.0.0
Requires-Dist: dateparser
Requires-Dist: numpy<2.0; python_version == "3.9"
Requires-Dist: pandas[excel]
Requires-Dist: pint!=0.21.*
Requires-Dist: pint<0.22; python_version < "3.9"
Requires-Dist: pint-pandas
Requires-Dist: plottoolbox>=105.0.1
Requires-Dist: pydantic>=2.0.0
Requires-Dist: scikit-learn
Requires-Dist: scipy
Requires-Dist: statsmodels
Requires-Dist: tabulate
